LICENSE
README.md
setup.cfg
setup.py
datara/__init__.py
datara.egg-info/PKG-INFO
datara.egg-info/SOURCES.txt
datara.egg-info/dependency_links.txt
datara.egg-info/requires.txt
datara.egg-info/top_level.txt